AUTHORS
COPYING
ChangeLog
MANIFEST.in
Makefile
NEWS.md
README.rst
THANKS
VERSION.py
__pkginfo__.py
cdio.py
iso9660.py
pycdio.py
pyiso9660.py
setup.cfg
setup.py
data/copying.iso
data/isofs-m1.bin
data/isofs-m1.cue
example/README
example/cd-read.py
example/cdtext.py
example/device.py
example/drives.py
example/eject.py
example/iso1.py
example/iso2.py
example/iso3.py
example/tracks.py
pycdio.egg-info/PKG-INFO
pycdio.egg-info/SOURCES.txt
pycdio.egg-info/dependency_links.txt
pycdio.egg-info/top_level.txt
swig/Makefile
swig/audio.swg
swig/cdtext.swg
swig/device.swg
swig/device_const.swg
swig/disc.swg
swig/pycdio.i
swig/pyiso9660.i
swig/read.swg
swig/track.swg
swig/types.swg
test/Makefile
test/cdda.bin
test/cdda.cue
test/cdda.toc
test/cdtext.toc
test/copying.iso
test/isofs-m1.bin
test/isofs-m1.cue
test/test-cdio.py
test/test-cdtext.py
test/test-iso.py
test/test-isocopy.py